README.md
setup.cfg
setup.py
distributions/Binomialdistribution.py
distributions/Gaussiandistribution.py
distributions/Generaldistribution.py
distributions/__init__.py
eratner_distributions.egg-info/PKG-INFO
eratner_distributions.egg-info/SOURCES.txt
eratner_distributions.egg-info/dependency_links.txt
eratner_distributions.egg-info/not-zip-safe
eratner_distributions.egg-info/top_level.txt