Metadata-Version: 1.0
Name: eratner-distributions
Version: 0.2
Summary: Gaussian distributions and Binomial Distributions
Home-page: UNKNOWN
Author: UNKNOWN
Author-email: UNKNOWN
License: UNKNOWN
Platform: UNKNOWN
